{
  "type": "minecraft:block",
  "pools": [
    {
      "bonus_rolls": 0.0,
      "conditions": [
        {
          "condition": "minecraft:survives_explosion"
        }
      ],
      "entries": [
        {
          "type": "minecraft:alternatives",
          "children": [
            {
              "type": "minecraft:item",
              "conditions": [
                {
                  "condition": "minecraft:match_tool",
                  "predicate": {
                    "enchantments": [
                      {
                        "enchantment": "minecraft:silk_touch",
                        "levels": {
                          "min": 1
                        }
                      }
                    ]
                  }
                }
              ],
              "name": "hallownest:solid_pale_ore"
            },
            {
              "type": "minecraft:item",
              "functions": [
                {
                  "add": false,
                  "count": 1.0,
                  "function": "minecraft:set_count"
                }
              ],
              "name": "hallownest:pale_ore"
            }
          ]
        }
      ],
      "rolls": 1.0
    }
  ]
}